cirdan/__init__.py
cirdan/decorators.py
cirdan/default.jinja2
cirdan/registry.py
cirdan/resource.py
cirdan-1.1.1.dist-info/DESCRIPTION.rst
cirdan-1.1.1.dist-info/METADATA
cirdan-1.1.1.dist-info/metadata.json
cirdan-1.1.1.dist-info/RECORD
cirdan-1.1.1.dist-info/top_level.txt
cirdan-1.1.1.dist-info/WHEEL
