Metadata-Version: 2.0
Name: cirdan
Version: 1.1.1
Summary: Decorator-based documentation generation for Falcon-based web applications.
Home-page: https://github.com/forana/python-cirdan
Author: Alex Foran
Author-email: alex@alexforan.com
License: UNKNOWN
Platform: UNKNOWN
Requires-Dist: Jinja2 (==2.7.3)
Requires-Dist: falcon (==0.3.0)
